{
  "formatVersion": 1,
  "database": {
    "version": 8,
    "identityHash": "2da97524aa2017837deda7fd27f3a14c",
    "entities": [
      {
        "tableName": "site_overide_ids",
        "createSql": "CREATE TABLE IF NOT EXISTS `${TABLE_NAME}` (`projectId` TEXT NOT NULL, `generalFormIds` TEXT, `scheduleFormIds` TEXT, `stagedFormIds` TEXT, PRIMARY KEY(`projectId`))",
        "fields": [
          {
            "fieldPath": "projectId",
            "columnName": "projectId",
            "affinity": "TEXT",
            "notNull": true
          },
          {
            "fieldPath": "generalFormIds",
            "columnName": "generalFormIds",
            "affinity": "TEXT",
            "notNull": false
          },
          {
            "fieldPath": "scheduleFormIds",
            "columnName": "scheduleFormIds",
            "affinity": "TEXT",
            "notNull": false
          },
          {
            "fieldPath": "stagedFormIds",
            "columnName": "stagedFormIds",
            "affinity": "TEXT",
            "notNull": false
          }
        ],
        "primaryKey": {
          "columnNames": [
            "projectId"
          ],
          "autoGenerate": false
        },
        "indices": [],
        "foreignKeys": []
      },
      {
        "tableName": "ProjectFilter",
        "createSql": "CREATE TABLE IF NOT EXISTS `${TABLE_NAME}` (`id` TEXT NOT NULL, `selectedRegionId` TEXT, `selectedRegionLabel` TEXT, PRIMARY KEY(`id`))",
        "fields": [
          {
            "fieldPath": "id",
            "columnName": "id",
            "affinity": "TEXT",
            "notNull": true
          },
          {
            "fieldPath": "selectedRegionId",
            "columnName": "selectedRegionId",
            "affinity": "TEXT",
            "notNull": false
          },
          {
            "fieldPath": "selectedRegionLabel",
            "columnName": "selectedRegionLabel",
            "affinity": "TEXT",
            "notNull": false
          }
        ],
        "primaryKey": {
          "columnNames": [
            "id"
          ],
          "autoGenerate": false
        },
        "indices": [],
        "foreignKeys": []
      },
      {
        "tableName": "sync",
        "createSql": "CREATE TABLE IF NOT EXISTS `${TABLE_NAME}` (`uid` INTEGER NOT NULL, `downloadingStatus` INTEGER NOT NULL, `title` TEXT, `detail` TEXT, `checked` INTEGER NOT NULL, `lastSyncDateTime` TEXT, `errorMessage` TEXT, `syncProgress` INTEGER NOT NULL, `syncTotal` INTEGER NOT NULL, `sync_message` TEXT, `is_determinate` INTEGER NOT NULL, PRIMARY KEY(`uid`))",
        "fields": [
          {
            "fieldPath": "uid",
            "columnName": "uid",
            "affinity": "INTEGER",
            "notNull": true
          },
          {
            "fieldPath": "downloadingStatus",
            "columnName": "downloadingStatus",
            "affinity": "INTEGER",
            "notNull": true
          },
          {
            "fieldPath": "title",
            "columnName": "title",
            "affinity": "TEXT",
            "notNull": false
          },
          {
            "fieldPath": "detail",
            "columnName": "detail",
            "affinity": "TEXT",
            "notNull": false
          },
          {
            "fieldPath": "checked",
            "columnName": "checked",
            "affinity": "INTEGER",
            "notNull": true
          },
          {
            "fieldPath": "lastSyncDateTime",
            "columnName": "lastSyncDateTime",
            "affinity": "TEXT",
            "notNull": false
          },
          {
            "fieldPath": "errorMessage",
            "columnName": "errorMessage",
            "affinity": "TEXT",
            "notNull": false
          },
          {
            "fieldPath": "syncProgress",
            "columnName": "syncProgress",
            "affinity": "INTEGER",
            "notNull": true
          },
          {
            "fieldPath": "syncTotal",
            "columnName": "syncTotal",
            "affinity": "INTEGER",
            "notNull": true
          },
          {
            "fieldPath": "syncMessage",
            "columnName": "sync_message",
            "affinity": "TEXT",
            "notNull": false
          },
          {
            "fieldPath": "isDeterminate",
            "columnName": "is_determinate",
            "affinity": "INTEGER",
            "notNull": true
          }
        ],
        "primaryKey": {
          "columnNames": [
            "uid"
          ],
          "autoGenerate": false
        },
        "indices": [],
        "foreignKeys": []
      },
      {
        "tableName": "site_upload_history",
        "createSql": "CREATE TABLE IF NOT EXISTS `${TABLE_NAME}` (`newSiteId` TEXT NOT NULL, `oldSiteId` TEXT, PRIMARY KEY(`newSiteId`))",
        "fields": [
          {
            "fieldPath": "newSiteId",
            "columnName": "newSiteId",
            "affinity": "TEXT",
            "notNull": true
          },
          {
            "fieldPath": "oldSiteId",
            "columnName": "oldSiteId",
            "affinity": "TEXT",
            "notNull": false
          }
        ],
        "primaryKey": {
          "columnNames": [
            "newSiteId"
          ],
          "autoGenerate": false
        },
        "indices": [],
        "foreignKeys": []
      }
    ],
    "setupQueries": [
      "CREATE TABLE IF NOT EXISTS room_master_table (id INTEGER PRIMARY KEY,identity_hash TEXT)",
      "INSERT OR REPLACE INTO room_master_table (id,identity_hash) VALUES(42, \"2da97524aa2017837deda7fd27f3a14c\")"
    ]
  }
}